[
  {
    "service": "5060",
    "name": "Snapchat Followers | No Refill - Max 1K - 200/Day - Worldwide",
    "type": "Default",
    "rate": "15.63",
    "min": "100",
    "max": "500",
    "dripfeed": false,
    "refill": false,
    "cancel": false,
    "category": "Snapchat \u279c \ud835\uddea\ud835\uddfc\ud835\uddff\ud835\uddf9\ud835\uddf1\ud835\ude04\ud835\uddf6\ud835\uddf1\ud835\uddf2"
  },
  {
    "service": "5171",
    "name": "Snapchat Followers | 30 Days Refill - Max 100K - 1k/Day - Worldwide",
    "type": "Default",
    "rate": "28.41",
    "min": "10",
    "max": "100000",
    "dripfeed": false,
    "refill": false,
    "cancel": false,
    "category": "Snapchat \u279c \ud835\uddea\ud835\uddfc\ud835\uddff\ud835\uddf9\ud835\uddf1\ud835\ude04\ud835\uddf6\ud835\uddf1\ud835\uddf2"
  },
  {
    "service": "5033",
    "name": "Snapchat Story Views | No Refill - Max 1k - 500/day - Worldwide",
    "type": "Default",
    "rate": "18.24",
    "min": "100",
    "max": "500",
    "dripfeed": false,
    "refill": false,
    "cancel": false,
    "category": "Snapchat \u279c \ud835\uddea\ud835\uddfc\ud835\uddff\ud835\uddf9\ud835\uddf1\ud835\ude04\ud835\uddf6\ud835\uddf1\ud835\uddf2"
  },
  {
    "service": "5742",
    "name": "Snapchat Story Views | 30 Days Refill - Max 100k - 500/day - Worldwide",
    "type": "Default",
    "rate": "28.36",
    "min": "10",
    "max": "100000",
    "dripfeed": false,
    "refill": false,
    "cancel": false,
    "category": "Snapchat \u279c \ud835\uddea\ud835\uddfc\ud835\uddff\ud835\uddf9\ud835\uddf1\ud835\ude04\ud835\uddf6\ud835\uddf1\ud835\uddf2"
  },
  {
    "service": "4867",
    "name": "Snapchat Followers - Arab - 30 Days Refill - Max 20K - 1k/Day",
    "type": "Default",
    "rate": "18.35",
    "min": "100",
    "max": "20000",
    "dripfeed": false,
    "refill": false,
    "cancel": false,
    "category": "Snapchat Followers \u279c \ud835\uddd4\ud835\uddff\ud835\uddee\ud835\uddef"
  },
  {
    "service": "5161",
    "name": "Snapchat Followers | Arab - Lifetime Refill - Max 100K - 1K/Day",
    "type": "Default",
    "rate": "33.95",
    "min": "50",
    "max": "100000",
    "dripfeed": false,
    "refill": false,
    "cancel": false,
    "category": "Snapchat Followers \u279c \ud835\uddd4\ud835\uddff\ud835\uddee\ud835\uddef"
  },
  {
    "service": "5021",
    "name": "Snapchat Followers [ Saudi Arabia \ud83c\uddf8\ud83c\udde6 ] 30 Days Refill - 500/Day",
    "type": "Default",
    "rate": "29.22",
    "min": "50",
    "max": "100000",
    "dripfeed": false,
    "refill": false,
    "cancel": false,
    "category": "Snapchat Followers \u279c \ud835\uddd4\ud835\uddff\ud835\uddee\ud835\uddef"
  },
  {
    "service": "5022",
    "name": "Snapchat Followers [ Bahrain \ud83c\udde7\ud83c\udded ] 30 Days Refill - 500/Day",
    "type": "Default",
    "rate": "29.22",
    "min": "50",
    "max": "100000",
    "dripfeed": false,
    "refill": false,
    "cancel": false,
    "category": "Snapchat Followers \u279c \ud835\uddd4\ud835\uddff\ud835\uddee\ud835\uddef"
  },
  {
    "service": "5030",
    "name": "Snapchat Followers [ Kuwait \ud83c\uddf0\ud83c\uddfc ] 30 Days Refill - 500/Day",
    "type": "Default",
    "rate": "29.22",
    "min": "50",
    "max": "100000",
    "dripfeed": false,
    "refill": false,
    "cancel": false,
    "category": "Snapchat Followers \u279c \ud835\uddd4\ud835\uddff\ud835\uddee\ud835\uddef"
  },
  {
    "service": "5032",
    "name": "Snapchat Followers [ UAE \ud83c\udde6\ud83c\uddea ] 30 Days Refill - 500/Day",
    "type": "Default",
    "rate": "29.22",
    "min": "50",
    "max": "100000",
    "dripfeed": false,
    "refill": false,
    "cancel": false,
    "category": "Snapchat Followers \u279c \ud835\uddd4\ud835\uddff\ud835\uddee\ud835\uddef"
  },
  {
    "service": "5035",
    "name": "Snapchat Followers [ Iraq \ud83c\uddee\ud83c\uddf6 ] 30 Days Refill - 500/Day",
    "type": "Default",
    "rate": "29.22",
    "min": "50",
    "max": "100000",
    "dripfeed": false,
    "refill": false,
    "cancel": false,
    "category": "Snapchat Followers \u279c \ud835\uddd4\ud835\uddff\ud835\uddee\ud835\uddef"
  },
  {
    "service": "5036",
    "name": "Snapchat Followers [ Qatar \ud83c\uddf6\ud83c\udde6 ] 30 Days Refill - 500/Day",
    "type": "Default",
    "rate": "29.22",
    "min": "50",
    "max": "100000",
    "dripfeed": false,
    "refill": false,
    "cancel": false,
    "category": "Snapchat Followers \u279c \ud835\uddd4\ud835\uddff\ud835\uddee\ud835\uddef"
  },
  {
    "service": "5039",
    "name": "Snapchat Followers [ Oman \ud83c\uddf4\ud83c\uddf2 ] 30 Days Refill - 500/Day",
    "type": "Default",
    "rate": "29.22",
    "min": "50",
    "max": "100000",
    "dripfeed": false,
    "refill": false,
    "cancel": false,
    "category": "Snapchat Followers \u279c \ud835\uddd4\ud835\uddff\ud835\uddee\ud835\uddef"
  },
  {
    "service": "5064",
    "name": "Snapchat Followers [ Jordan \ud83c\uddef\ud83c\uddf4 ] 30 Days Refill - 500/Day",
    "type": "Default",
    "rate": "29.22",
    "min": "50",
    "max": "100000",
    "dripfeed": false,
    "refill": false,
    "cancel": false,
    "category": "Snapchat Followers \u279c \ud835\uddd4\ud835\uddff\ud835\uddee\ud835\uddef"
  },
  {
    "service": "5029",
    "name": "Snapchat Followers [ Egypt \ud83c\uddea\ud83c\uddec ] 30 Days Refill - 500/Day",
    "type": "Default",
    "rate": "29.22",
    "min": "50",
    "max": "100000",
    "dripfeed": false,
    "refill": false,
    "cancel": false,
    "category": "Snapchat Followers \u279c \ud835\uddd4\ud835\uddff\ud835\uddee\ud835\uddef"
  },
  {
    "service": "5082",
    "name": "Snapchat Story Views | Arab - First 5 Stories - Lifetime Refill - 20K",
    "type": "Default",
    "rate": "18.43",
    "min": "100",
    "max": "20000",
    "dripfeed": false,
    "refill": false,
    "cancel": false,
    "category": "Snapchat Story Views \u279c \ud835\uddd4\ud835\uddff\ud835\uddee\ud835\uddef"
  },
  {
    "service": "5068",
    "name": "Snapchat Story Views | Arab - All Stories - Lifetime Refill - Max 50K",
    "type": "Default",
    "rate": "26.83",
    "min": "50",
    "max": "50000",
    "dripfeed": false,
    "refill": false,
    "cancel": false,
    "category": "Snapchat Story Views \u279c \ud835\uddd4\ud835\uddff\ud835\uddee\ud835\uddef"
  },
  {
    "service": "5073",
    "name": "Snapchat 100 Story Views [ Saudi Arabia \ud83c\uddf8\ud83c\udde6 ] All Stories",
    "type": "Package",
    "rate": "3.50",
    "min": "1",
    "max": "1",
    "dripfeed": false,
    "refill": false,
    "cancel": false,
    "category": "Snapchat Story Views \u279c \ud835\uddd4\ud835\uddff\ud835\uddee\ud835\uddef"
  },
  {
    "service": "5053",
    "name": "Snapchat 100 Story Views [ UAE \ud83c\udde6\ud83c\uddea ] All Stories",
    "type": "Package",
    "rate": "3.11",
    "min": "1",
    "max": "1",
    "dripfeed": false,
    "refill": false,
    "cancel": false,
    "category": "Snapchat Story Views \u279c \ud835\uddd4\ud835\uddff\ud835\uddee\ud835\uddef"
  },
  {
    "service": "5046",
    "name": "Snapchat 100 Story Views [ Kuwait \ud83c\uddf0\ud83c\uddfc ]  All Stories",
    "type": "Package",
    "rate": "3.11",
    "min": "1",
    "max": "1",
    "dripfeed": false,
    "refill": false,
    "cancel": false,
    "category": "Snapchat Story Views \u279c \ud835\uddd4\ud835\uddff\ud835\uddee\ud835\uddef"
  },
  {
    "service": "5052",
    "name": "Snapchat 100 Story Views [ Qatar \ud83c\uddf6\ud83c\udde6 ] All Stories",
    "type": "Package",
    "rate": "3.11",
    "min": "1",
    "max": "1",
    "dripfeed": false,
    "refill": false,
    "cancel": false,
    "category": "Snapchat Story Views \u279c \ud835\uddd4\ud835\uddff\ud835\uddee\ud835\uddef"
  },
  {
    "service": "5027",
    "name": "Snapchat 100 Story Views [ Oman \ud83c\uddf4\ud83c\uddf2 ] All Stories",
    "type": "Package",
    "rate": "3.11",
    "min": "1",
    "max": "1",
    "dripfeed": false,
    "refill": false,
    "cancel": false,
    "category": "Snapchat Story Views \u279c \ud835\uddd4\ud835\uddff\ud835\uddee\ud835\uddef"
  },
  {
    "service": "5055",
    "name": "Snapchat 100 Story Views [ Bahrain \ud83c\udde7\ud83c\udded ] All Stories",
    "type": "Package",
    "rate": "3.11",
    "min": "1",
    "max": "1",
    "dripfeed": false,
    "refill": false,
    "cancel": false,
    "category": "Snapchat Story Views \u279c \ud835\uddd4\ud835\uddff\ud835\uddee\ud835\uddef"
  },
  {
    "service": "5066",
    "name": "Snapchat 100 Story Views [ Iraq \ud83c\uddee\ud83c\uddf6 ] All Stories",
    "type": "Package",
    "rate": "3.11",
    "min": "1",
    "max": "1",
    "dripfeed": false,
    "refill": false,
    "cancel": false,
    "category": "Snapchat Story Views \u279c \ud835\uddd4\ud835\uddff\ud835\uddee\ud835\uddef"
  },
  {
    "service": "5001",
    "name": "Snapchat Spotlight [Views] - 100% Real - 500/Day - Worldwide \ud83c\udf0e",
    "type": "Default",
    "rate": "33.98",
    "min": "50",
    "max": "1000000",
    "dripfeed": false,
    "refill": false,
    "cancel": false,
    "category": "Snapchat Spotlights \u279c \ud835\udde0\ud835\uddfc\ud835\uddfb\ud835\uddf2\ud835\ude01\ud835\uddf6\ud835\ude07\ud835\uddee\ud835\uddef\ud835\uddf9\ud835\uddf2"
  },
  {
    "service": "5005",
    "name": "Snapchat Spotlight [Likes] - 100% Real - 500/Day - Worldwide \ud83c\udf0e",
    "type": "Default",
    "rate": "39.75",
    "min": "50",
    "max": "1000000",
    "dripfeed": false,
    "refill": false,
    "cancel": false,
    "category": "Snapchat Spotlights \u279c \ud835\udde0\ud835\uddfc\ud835\uddfb\ud835\uddf2\ud835\ude01\ud835\uddf6\ud835\ude07\ud835\uddee\ud835\uddef\ud835\uddf9\ud835\uddf2"
  },
  {
    "service": "5034",
    "name": "Snapchat Spotlight [Save] - 100% Real - 500/Day - Worldwide \ud83c\udf0d",
    "type": "Default",
    "rate": "61.46",
    "min": "50",
    "max": "1000000",
    "dripfeed": false,
    "refill": false,
    "cancel": false,
    "category": "Snapchat Spotlights \u279c \ud835\udde0\ud835\uddfc\ud835\uddfb\ud835\uddf2\ud835\ude01\ud835\uddf6\ud835\ude07\ud835\uddee\ud835\uddef\ud835\uddf9\ud835\uddf2"
  },
  {
    "service": "5048",
    "name": "Snapchat Spotlight [Share] - 100% Real - 500/Day - Worldwide \ud83c\udf0d",
    "type": "Default",
    "rate": "34.63",
    "min": "50",
    "max": "1000000",
    "dripfeed": false,
    "refill": false,
    "cancel": false,
    "category": "Snapchat Spotlights \u279c \ud835\udde0\ud835\uddfc\ud835\uddfb\ud835\uddf2\ud835\ude01\ud835\uddf6\ud835\ude07\ud835\uddee\ud835\uddef\ud835\uddf9\ud835\uddf2"
  },
  {
    "service": "5014",
    "name": "Snapchat Spotlight [Comments] - 100% Real - 500/Day - Worldwide \ud83c\udf0d",
    "type": "Custom Comments",
    "rate": "54.27",
    "min": "20",
    "max": "1000000",
    "dripfeed": false,
    "refill": false,
    "cancel": false,
    "category": "Snapchat Spotlights \u279c \ud835\udde0\ud835\uddfc\ud835\uddfb\ud835\uddf2\ud835\ude01\ud835\uddf6\ud835\ude07\ud835\uddee\ud835\uddef\ud835\uddf9\ud835\uddf2"
  },
  {
    "service": "5062",
    "name": "Snapchat Spotlight [Comment Like] - 100% Real - 500/Day - Worldwide \ud83c\udf0d",
    "type": "Comment Likes",
    "rate": "63.82",
    "min": "50",
    "max": "1000000",
    "dripfeed": false,
    "refill": false,
    "cancel": false,
    "category": "Snapchat Spotlights \u279c \ud835\udde0\ud835\uddfc\ud835\uddfb\ud835\uddf2\ud835\ude01\ud835\uddf6\ud835\ude07\ud835\uddee\ud835\uddef\ud835\uddf9\ud835\uddf2"
  },
  {
    "service": "5741",
    "name": "Snapchat Public Profile [Subscribes] - 100% Real - 500/Day - Worldwide \ud83c\udf0d",
    "type": "Default",
    "rate": "48.92",
    "min": "50",
    "max": "1000000",
    "dripfeed": false,
    "refill": false,
    "cancel": false,
    "category": "Snapchat Spotlights \u279c \ud835\udde0\ud835\uddfc\ud835\uddfb\ud835\uddf2\ud835\ude01\ud835\uddf6\ud835\ude07\ud835\uddee\ud835\uddef\ud835\uddf9\ud835\uddf2"
  },
  {
    "service": "5000",
    "name": "Snapchat Spotlight [Views] - 100% Real - 500/Day - Arab \ud83c\udde6\ud83c\uddea",
    "type": "Default",
    "rate": "34.36",
    "min": "50",
    "max": "1000000",
    "dripfeed": false,
    "refill": false,
    "cancel": false,
    "category": "Snapchat Spotlights \u279c \ud835\udde0\ud835\uddfc\ud835\uddfb\ud835\uddf2\ud835\ude01\ud835\uddf6\ud835\ude07\ud835\uddee\ud835\uddef\ud835\uddf9\ud835\uddf2"
  },
  {
    "service": "5002",
    "name": "Snapchat Spotlight [Likes] - 100% Real - 500/Day - Arab \ud83c\udde6\ud83c\uddea",
    "type": "Default",
    "rate": "39.75",
    "min": "50",
    "max": "1000000",
    "dripfeed": false,
    "refill": false,
    "cancel": false,
    "category": "Snapchat Spotlights \u279c \ud835\udde0\ud835\uddfc\ud835\uddfb\ud835\uddf2\ud835\ude01\ud835\uddf6\ud835\ude07\ud835\uddee\ud835\uddef\ud835\uddf9\ud835\uddf2"
  },
  {
    "service": "5015",
    "name": "Snapchat Spotlight [Save] - 100% Real - 500/Day - Arab \ud83c\udde6\ud83c\uddea",
    "type": "Default",
    "rate": "63.65",
    "min": "50",
    "max": "1000000",
    "dripfeed": false,
    "refill": false,
    "cancel": false,
    "category": "Snapchat Spotlights \u279c \ud835\udde0\ud835\uddfc\ud835\uddfb\ud835\uddf2\ud835\ude01\ud835\uddf6\ud835\ude07\ud835\uddee\ud835\uddef\ud835\uddf9\ud835\uddf2"
  },
  {
    "service": "5047",
    "name": "Snapchat Spotlight [Share] - 100% Real - 500/Day - Arab \ud83c\udde6\ud83c\uddea",
    "type": "Default",
    "rate": "38.74",
    "min": "50",
    "max": "1000000",
    "dripfeed": false,
    "refill": false,
    "cancel": false,
    "category": "Snapchat Spotlights \u279c \ud835\udde0\ud835\uddfc\ud835\uddfb\ud835\uddf2\ud835\ude01\ud835\uddf6\ud835\ude07\ud835\uddee\ud835\uddef\ud835\uddf9\ud835\uddf2"
  },
  {
    "service": "5013",
    "name": "Snapchat Spotlight [Comments] - 100% Real - 500/Day - Arab \ud83c\udde6\ud83c\uddea",
    "type": "Custom Comments",
    "rate": "58.84",
    "min": "20",
    "max": "1000000",
    "dripfeed": false,
    "refill": false,
    "cancel": false,
    "category": "Snapchat Spotlights \u279c \ud835\udde0\ud835\uddfc\ud835\uddfb\ud835\uddf2\ud835\ude01\ud835\uddf6\ud835\ude07\ud835\uddee\ud835\uddef\ud835\uddf9\ud835\uddf2"
  },
  {
    "service": "5061",
    "name": "Snapchat Spotlight [Comment Like] - 100% Real - 500/Day - Arab \ud83c\udde6\ud83c\uddea",
    "type": "Comment Likes",
    "rate": "65.14",
    "min": "50",
    "max": "1000000",
    "dripfeed": false,
    "refill": false,
    "cancel": false,
    "category": "Snapchat Spotlights \u279c \ud835\udde0\ud835\uddfc\ud835\uddfb\ud835\uddf2\ud835\ude01\ud835\uddf6\ud835\ude07\ud835\uddee\ud835\uddef\ud835\uddf9\ud835\uddf2"
  },
  {
    "service": "5740",
    "name": "Snapchat Public Profile [Subscribes] - 100% Real - 500/Day - Arab \ud83c\udde6\ud83c\uddea",
    "type": "Default",
    "rate": "49.43",
    "min": "50",
    "max": "1000000",
    "dripfeed": false,
    "refill": false,
    "cancel": false,
    "category": "Snapchat Spotlights \u279c \ud835\udde0\ud835\uddfc\ud835\uddfb\ud835\uddf2\ud835\ude01\ud835\uddf6\ud835\ude07\ud835\uddee\ud835\uddef\ud835\uddf9\ud835\uddf2"
  },
  {
    "service": "5711",
    "name": "Snapchat Spotlight [Views] - No Refill - Max 50k - 1k/Day",
    "type": "Default",
    "rate": "32.87",
    "min": "100",
    "max": "50000",
    "dripfeed": false,
    "refill": false,
    "cancel": false,
    "category": "Snapchat Spotlights \u279c \ud835\udde0\ud835\uddfc\ud835\uddfb\ud835\uddf2\ud835\ude01\ud835\uddf6\ud835\ude07\ud835\uddee\ud835\uddef\ud835\uddf9\ud835\uddf2"
  },
  {
    "service": "5072",
    "name": "Snapchat Spotlight [Likes] - No Refill - Max 50k - 1k/Day",
    "type": "Default",
    "rate": "37.23",
    "min": "100",
    "max": "50000",
    "dripfeed": false,
    "refill": false,
    "cancel": false,
    "category": "Snapchat Spotlights \u279c \ud835\udde0\ud835\uddfc\ud835\uddfb\ud835\uddf2\ud835\ude01\ud835\uddf6\ud835\ude07\ud835\uddee\ud835\uddef\ud835\uddf9\ud835\uddf2"
  },
  {
    "service": "5787",
    "name": "Snapchat Spotlight [Subscribes] - No Refill - Max 50k - 1k/day",
    "type": "Default",
    "rate": "36.34",
    "min": "100",
    "max": "50000",
    "dripfeed": false,
    "refill": false,
    "cancel": false,
    "category": "Snapchat Spotlights \u279c \ud835\udde0\ud835\uddfc\ud835\uddfb\ud835\uddf2\ud835\ude01\ud835\uddf6\ud835\ude07\ud835\uddee\ud835\uddef\ud835\uddf9\ud835\uddf2"
  },
  {
    "service": "8970",
    "name": "Snapchat Daily Engagement | 50 Follow + 50 Story Daily for 30 Days [Arab]",
    "type": "Package",
    "rate": "79.00",
    "min": "1",
    "max": "1",
    "dripfeed": false,
    "refill": false,
    "cancel": false,
    "category": "Snapchat Subscription \u279c \ud835\uddd7\ud835\uddee\ud835\uddf6\ud835\uddf9\ud835\ude06 \ud835\uddd4\ud835\uddf1\ud835\ude00 \u207b\u1d3a\u1d31\u1d42\u207b \ud83d\udd25"
  },
  {
    "service": "8971",
    "name": "Snapchat Daily Engagement | 100 Follow + 100 Story Daily for 30 Days [Arab]",
    "type": "Package",
    "rate": "149.00",
    "min": "1",
    "max": "1",
    "dripfeed": false,
    "refill": false,
    "cancel": false,
    "category": "Snapchat Subscription \u279c \ud835\uddd7\ud835\uddee\ud835\uddf6\ud835\uddf9\ud835\ude06 \ud835\uddd4\ud835\uddf1\ud835\ude00 \u207b\u1d3a\u1d31\u1d42\u207b \ud83d\udd25"
  },
  {
    "service": "8972",
    "name": "Snapchat Daily Engagement | 200 Follow + 200 Story Daily for 30 Days [Arab]",
    "type": "Package",
    "rate": "287.00",
    "min": "1",
    "max": "1",
    "dripfeed": false,
    "refill": false,
    "cancel": false,
    "category": "Snapchat Subscription \u279c \ud835\uddd7\ud835\uddee\ud835\uddf6\ud835\uddf9\ud835\ude06 \ud835\uddd4\ud835\uddf1\ud835\ude00 \u207b\u1d3a\u1d31\u1d42\u207b \ud83d\udd25"
  },
  {
    "service": "8973",
    "name": "Snapchat Daily Engagement | 300 Follow + 300 Story Daily for 30 Days [Arab]",
    "type": "Package",
    "rate": "425.00",
    "min": "1",
    "max": "1",
    "dripfeed": false,
    "refill": false,
    "cancel": false,
    "category": "Snapchat Subscription \u279c \ud835\uddd7\ud835\uddee\ud835\uddf6\ud835\uddf9\ud835\ude06 \ud835\uddd4\ud835\uddf1\ud835\ude00 \u207b\u1d3a\u1d31\u1d42\u207b \ud83d\udd25"
  },
  {
    "service": "8974",
    "name": "Snapchat Daily Engagement | 500 Follow + 500 Story Daily for 30 Days [Arab]",
    "type": "Package",
    "rate": "689.00",
    "min": "1",
    "max": "1",
    "dripfeed": false,
    "refill": false,
    "cancel": false,
    "category": "Snapchat Subscription \u279c \ud835\uddd7\ud835\uddee\ud835\uddf6\ud835\uddf9\ud835\ude06 \ud835\uddd4\ud835\uddf1\ud835\ude00 \u207b\u1d3a\u1d31\u1d42\u207b \ud83d\udd25"
  },
  {
    "service": "5801",
    "name": "Snapchat Direct Message DM Mass [Choose Country] Real Ads - Min 100K",
    "type": "Invites from Groups",
    "rate": "20.00",
    "min": "100000",
    "max": "1000000",
    "dripfeed": false,
    "refill": false,
    "cancel": false,
    "category": "Snapchat Direct Message \u279c \ud835\udde0\ud835\uddee\ud835\ude00\ud835\ude00 \ud835\uddd7\ud835\udde0 \u207b\u1d3a\u1d31\u1d42\u207b \ud83d\udd25"
  },
  {
    "service": "5802",
    "name": "Snapchat Direct Message DM Mass [Choose Country] Real Ads - Min 50K",
    "type": "Invites from Groups",
    "rate": "30.00",
    "min": "50000",
    "max": "100000",
    "dripfeed": false,
    "refill": false,
    "cancel": false,
    "category": "Snapchat Direct Message \u279c \ud835\udde0\ud835\uddee\ud835\ude00\ud835\ude00 \ud835\uddd7\ud835\udde0 \u207b\u1d3a\u1d31\u1d42\u207b \ud83d\udd25"
  },
  {
    "service": "5803",
    "name": "Snapchat Direct Message DM Mass [Choose Country] Real Ads - Min 10K",
    "type": "Invites from Groups",
    "rate": "40.00",
    "min": "10000",
    "max": "50000",
    "dripfeed": false,
    "refill": false,
    "cancel": false,
    "category": "Snapchat Direct Message \u279c \ud835\udde0\ud835\uddee\ud835\ude00\ud835\ude00 \ud835\uddd7\ud835\udde0 \u207b\u1d3a\u1d31\u1d42\u207b \ud83d\udd25"
  },
  {
    "service": "5804",
    "name": "Snapchat Direct Message DM Mass [Choose Country] Real Ads - Min 1K",
    "type": "Invites from Groups",
    "rate": "50.00",
    "min": "1000",
    "max": "10000",
    "dripfeed": false,
    "refill": false,
    "cancel": false,
    "category": "Snapchat Direct Message \u279c \ud835\udde0\ud835\uddee\ud835\ude00\ud835\ude00 \ud835\uddd7\ud835\udde0 \u207b\u1d3a\u1d31\u1d42\u207b \ud83d\udd25"
  },
  {
    "service": "5870",
    "name": "Snapchat Direct Message DM Mass [Your Custom List] Real Advertisement",
    "type": "Mentions with Hashtags",
    "rate": "35.00",
    "min": "100",
    "max": "10000000",
    "dripfeed": false,
    "refill": false,
    "cancel": false,
    "category": "Snapchat Direct Message \u279c \ud835\udde0\ud835\uddee\ud835\ude00\ud835\ude00 \ud835\uddd7\ud835\udde0 \u207b\u1d3a\u1d31\u1d42\u207b \ud83d\udd25"
  }
]